darksecret/__init__.py
darksecret/base.py
darksecret/fernet.py
darksecret/secret.py
darksecret-202303151118.dist-info/METADATA
darksecret-202303151118.dist-info/WHEEL
darksecret-202303151118.dist-info/top_level.txt
darksecret-202303151118.dist-info/RECORD
