Metadata-Version: 2.1
Name: darksecret
Version: 202303151118
Summary: darksecret
Home-page: https://github.com/1007530194
Author: niuliangtao
Author-email: 1007530194@qq.com
Requires-Dist: darkbuild
Requires-Dist: sqlalchemy
